{"description": "", "citation": "", "homepage": "", "license": "", "features": {"Tweet": {"dtype": "string", "_type": "Value"}, "Slang (yes/no)": {"dtype": "string", "_type": "Value"}}, "builder_name": "csv", "dataset_name": "slang_data", "config_name": "default", "version": {"version_str": "0.0.0", "major": 0, "minor": 0, "patch": 0}, "splits": {"train": {"name": "train", "num_bytes": 228520, "num_examples": 5000, "dataset_name": "slang_data"}}, "download_checksums": {"hf://datasets/nikesh66/Slang-Dataset@0c9bc18469ead579bbc540e4f765c1edaf07312c/slang_tweets.csv": {"num_bytes": 199161, "checksum": null}}, "download_size": 199161, "dataset_size": 228520, "size_in_bytes": 427681}